taxonomy_matcher/__init__.py
taxonomy_matcher/__main__.py
taxonomy_matcher/data_saver.py
taxonomy_matcher/data_utils.py
taxonomy_matcher/matched_phrase.py
taxonomy_matcher/matcher.py
taxonomy_matcher/token_position.py
taxonomy_matcher/token_trie.py
taxonomy_matcher/match_patterns/__init__.py
taxonomy_matcher/match_patterns/patterns.py
taxonomy_matcher/match_patterns/patterns_ct.py
taxonomy_matcher/match_patterns/patterns_gz.py
taxonomy_matcher/match_patterns/patterns_nt.py
taxonomy_matcher-0.0.9.dist-info/AUTHORS.rst
taxonomy_matcher-0.0.9.dist-info/LICENSE
taxonomy_matcher-0.0.9.dist-info/METADATA
taxonomy_matcher-0.0.9.dist-info/WHEEL
taxonomy_matcher-0.0.9.dist-info/entry_points.txt
taxonomy_matcher-0.0.9.dist-info/top_level.txt
taxonomy_matcher-0.0.9.dist-info/RECORD
