Metadata-Version: 2.1
Name: taxonomy-matcher
Version: 0.0.9
Summary: Python tool to match phrases listed in the taxonomy
Home-page: https://github.com/tilaboy/taxonomy-matcher
Author: Chao Li
Author-email: chaoli.job@gmail.com
License: MIT license
Keywords: taxonomy-matcher
Platform: UNKNOWN
Classifier: Development Status :: 2 - Pre-Alpha
Classifier: Intended Audience :: Developers
Classifier: License :: OSI Approved :: MIT License
Classifier: Natural Language :: English
Classifier: Programming Language :: Python :: 3.5
Classifier: Programming Language :: Python :: 3.6
Classifier: Programming Language :: Python :: 3.7
Requires-Dist: easy-tokenizer (>=0.0.8)
